Metadata-Version: 2.1
Name: simple-plugin-manager
Version: 0.1.1
Summary: Simple Plugin Manager
Home-page: https://github.com/fscherf/simple-plugin-manager
Author: Florian Scherf
Author-email: mail@florianscherf.de
License: MIT
Platform: UNKNOWN
Classifier: Development Status :: 4 - Beta
Classifier: Intended Audience :: Developers
Classifier: License :: OSI Approved :: MIT License
Classifier: Natural Language :: English
Classifier: Programming Language :: Python
Classifier: Programming Language :: Python :: 3
Classifier: Programming Language :: Python :: 3 :: Only
Classifier: Topic :: Software Development :: Libraries
Classifier: Topic :: System :: Software Distribution
License-File: LICENSE.txt
